<?xml version="1.0" encoding="UTF-8"?>
<StructureDefinition xmlns="http://hl7.org/fhir" xmlns:xsi="http://www.w3.org/2001/XMLSchema-instance" xsi:schemaLocation="http://hl7.org/fhir ../../input-cache/schemas/R4/fhir-single.xsd">
  <id value="elementdefinition-json-name"/>
  <extension url="http://hl7.org/fhir/StructureDefinition/structuredefinition-fmm">
    <valueInteger value="2"/>
  </extension>
  <url value="http://hl7.org/fhir/tools/StructureDefinition/elementdefinition-json-name"/>
  <name value="JsonPropertyName"/>
  <title value="Json Property Name Extension"/>
  <status value="active"/>
  <experimental value="true"/>
  <publisher value="HL7 International / FHIR Infrastructure"/>
  <contact>
    <telecom>
      <system value="url"/>
      <value value="http://hl7.org/Special/committees/fhir-i"/>
    </telecom>
  </contact>
  <description value="Provides the JSON property name for when the JSON name is not a valid element name, or on the root of a type to give the type itself an element name"/>
  <jurisdiction>
    <coding>
      <system value="http://unstats.un.org/unsd/methods/m49/m49.htm"/>
      <code value="001"/>
    </coding>
  </jurisdiction>  
  <fhirVersion value="4.0.1"/>
  <kind value="complex-type"/>
  <abstract value="false"/>
  <context>
    <type value="element"/>
    <expression value="ElementDefinition"/>
  </context>
  <type value="Extension"/>
  <baseDefinition value="http://hl7.org/fhir/StructureDefinition/Extension"/>
  <derivation value="constraint"/>
  <differential>
   <element id="Extension">
      <path value="Extension"/> 
      <short value="JSON property name (when the JSON name is not a valid element name, a name for the type)"/> 
      <definition value="Provides the JSON property name for when the JSON name is not a valid element name, or on the root of a type to give the type itself an element name"/> 
      <min value="0"/> 
      <max value="*"/> 
    </element> 

    <element id="Extension.extension">
      <path value="Extension.extension"/> 
      <max value="0"/> 
    </element> 

    <element id="Extension.url">
      <path value="Extension.url"/> 
      <fixedUri value="http://hl7.org/fhir/tools/StructureDefinition/elementdefinition-json-name"/> 
    </element> 
    <element id="Extension.value[x]">
      <path value="Extension.value[x]"/> 
      <min value="1"/> 
      <max value="1"/>
      <type>
        <code value="string"/>
      </type>
    </element> 
  </differential>
</StructureDefinition>
